sandpaper_py/__init__.py
sandpaper_py/exporter.py
sandpaper_py/extractor.py
sandpaper_py/menu.py
sandpaper_py/sandpaper.py
sandpaper_py/scraper.py
sandpaper_py-0.1.0.dist-info/METADATA
sandpaper_py-0.1.0.dist-info/WHEEL
sandpaper_py-0.1.0.dist-info/entry_points.txt
sandpaper_py-0.1.0.dist-info/licenses/LICENSE
sandpaper_py-0.1.0.dist-info/RECORD
