Metadata-Version: 2.4
Name: sandpaper-py
Version: 0.1.0
Summary: SandPaper is a package for scraping web pages with Playwright and exporting structured data to CSV.
Project-URL: Homepage, https://github.com/Aaryan-Dadu/SandPaper
Author-email: Aaryan Dadu <aaryandadu5157@gmail.com>
License-Expression: MIT
License-File: LICENSE
Classifier: Operating System :: OS Independent
Classifier: Programming Language :: Python :: 3
Requires-Python: >=3.9
Requires-Dist: beautifulsoup4
Requires-Dist: pandas
Requires-Dist: playwright
Requires-Dist: questionary
Requires-Dist: rich
Requires-Dist: tldextract
